luminescent/__init__.py
luminescent/calibration.py
luminescent/constants.py
luminescent/gcells.py
luminescent/generic_tech.py
luminescent/layers.py
luminescent/log.py
luminescent/materials.py
luminescent/mesh.py
luminescent/movie.py
luminescent/opt.py
luminescent/pcells.py
luminescent/picToGDS.py
luminescent/setup.py
luminescent/sol.py
luminescent/sparams.py
luminescent/utils.py
luminescent/meta/__init__.py
luminescent/meta/sparams.py
luminescent/pic/__init__.py
luminescent-3.1.4.dist-info/licenses/LICENSE
tests/__init__.py
luminescent-3.1.4.dist-info/METADATA
luminescent-3.1.4.dist-info/WHEEL
luminescent-3.1.4.dist-info/top_level.txt
luminescent-3.1.4.dist-info/RECORD
