Metadata-Version: 2.4
Name: luminescent
Version: 3.1.4
Summary: GPU-accelerated fully differentiable FDTD for photonics and RF
Author: Paul Shen
Author-email: pxshen@alumni.stanford.edu
License-File: LICENSE
Requires-Dist: gdsfactory
Requires-Dist: electromagneticpython
Requires-Dist: sortedcontainers
Requires-Dist: scikit-rf
Requires-Dist: opencv-python
Requires-Dist: femwell
Requires-Dist: rasterio
Requires-Dist: rtree
Requires-Dist: gmsh
Requires-Dist: manifold3d
Requires-Dist: pymeshlab
Requires-Dist: pyvista
Requires-Dist: google-cloud-storage
Requires-Dist: requests
Requires-Dist: ImageIO
Dynamic: author
Dynamic: author-email
Dynamic: license-file
Dynamic: requires-dist
Dynamic: summary
